streamlit_date_picker/__init__.py
streamlit_date_picker/frontend/build/asset-manifest.json
streamlit_date_picker/frontend/build/index.html
streamlit_date_picker/frontend/build/manifest.json
streamlit_date_picker/frontend/build/robots.txt
streamlit_date_picker/frontend/build/static/js/main.78ff4c09.js
streamlit_date_picker/frontend/build/static/js/main.78ff4c09.js.LICENSE.txt
streamlit_date_picker/frontend/build/static/js/main.78ff4c09.js.map
streamlit_date_picker/frontend/build/static/js/main.9b51e274.js
streamlit_date_picker/frontend/build/static/js/main.9b51e274.js.LICENSE.txt
streamlit_date_picker/frontend/build/static/js/main.9b51e274.js.map
streamlit_date_picker/frontend/build/static/js/main.c56b26ff.js
streamlit_date_picker/frontend/build/static/js/main.c56b26ff.js.LICENSE.txt
streamlit_date_picker/frontend/build/static/js/main.c56b26ff.js.map
streamlit_date_picker-0.0.5.dist-info/LICENSE
streamlit_date_picker-0.0.5.dist-info/METADATA
streamlit_date_picker-0.0.5.dist-info/WHEEL
streamlit_date_picker-0.0.5.dist-info/top_level.txt
streamlit_date_picker-0.0.5.dist-info/RECORD
