Metadata-Version: 2.1
Name: streamlit-date-picker
Version: 0.0.5
Summary: this is date picker for streamlit
Home-page: https://github.com/imdreamer2018/streamlit-date-picker
Author: Yang Qian
Author-email: qian.yang2@thoughtworks.com
Requires-Python: >=3.8
License-File: LICENSE
Requires-Dist: streamlit>=1.27.0
